broadsoftxchange/__init__.py
broadsoftxchange/items.py
broadsoftxchange/pipelines.py
broadsoftxchange/settings.py
broadsoftxchange/spiders/__init__.py
broadsoftxchange/spiders/documentation.py
broadsoftxchange/spiders/software.py
scrapy_broadsoftxchange-1.17.dist-info/DESCRIPTION.rst
scrapy_broadsoftxchange-1.17.dist-info/METADATA
scrapy_broadsoftxchange-1.17.dist-info/RECORD
scrapy_broadsoftxchange-1.17.dist-info/WHEEL
scrapy_broadsoftxchange-1.17.dist-info/metadata.json
scrapy_broadsoftxchange-1.17.dist-info/top_level.txt
