Metadata-Version: 2.0
Name: scrapy-broadsoftxchange
Version: 1.17
Summary: Download documents and published software from Broadsoft Xchange
Home-page: https://github.com/lukebeer/scrapy-broadsoftxchange
Author: Luke Berezynskyj (Aka Beer)
Author-email: mail@luke.beer
License: MIT
Keywords: scrapy broadsoft broadworks xchange
Platform: UNKNOWN
Classifier: Development Status :: 5 - Production/Stable
Classifier: Intended Audience :: Telecommunications Industry
Classifier: License :: OSI Approved :: MIT License
Classifier: Operating System :: OS Independent
Classifier: Programming Language :: Python
Classifier: Topic :: Internet :: WWW/HTTP
Requires-Dist: distribute
Requires-Dist: scrapy
